logger_pauwels/Data.py
logger_pauwels/Logger.py
logger_pauwels/__init__.py
logger_pauwels-0.1.7.dist-info/licenses/LICENSE
logger_pauwels-0.1.7.dist-info/METADATA
logger_pauwels-0.1.7.dist-info/WHEEL
logger_pauwels-0.1.7.dist-info/top_level.txt
logger_pauwels-0.1.7.dist-info/RECORD
