Metadata-Version: 2.4
Name: logger-pauwels
Version: 0.1.7
Summary: Simple logger to have fancy logs :D
Author-email: Tom Pauwels <tom.j.pauwels@gmail.com>
License: MIT License
Project-URL: Homepage, https://github.com/PauwelsTom/Python-Logger
Project-URL: Repository, https://github.com/PauwelsTom/Python-Logger
Project-URL: Issues, https://github.com/PauwelsTom/Python-Logger/issues
Requires-Python: >=3.8
License-File: LICENSE
Dynamic: license-file
